func_e/FUNC_E.py
func_e/__init__.py
func_e/cmd.py
func_e/vocabs/GO.py
func_e/vocabs/IPR.py
func_e/vocabs/KEGG.py
func_e/vocabs/Pfam.py
func_e/vocabs/__init__.py
func_e/vocabs/all.py
test/__init__.py
func_e-2.0.1.dist-info/LICENSE.txt
func_e-2.0.1.dist-info/METADATA
func_e-2.0.1.dist-info/WHEEL
func_e-2.0.1.dist-info/entry_points.txt
func_e-2.0.1.dist-info/top_level.txt
func_e-2.0.1.dist-info/RECORD
