Metadata-Version: 2.1
Name: func-e
Version: 2.0.1
Summary: FUNC-E is a python library and script for functional enrichment of gene lists. It follows a similar approach to that of DAVID (https://david.ncifcrf.gov/) in that it performs enrichment analysis using a Fisher's test but then clusters enriched annotations using Kappa Statistics. FUNC-E allows the user to provide their own annotation lists. It is fully executable on a UNIX command-line.
Home-page: https://systemsgenetics.github.io/FUNC-E/
Author: Ficklin and Feltus computational Labs (Washington State University & Clemson University)
License: GNU General Public License v3.0
Requires-Python: >=3.6
License-File: LICENSE.txt
Requires-Dist: numpy
Requires-Dist: pandas
Requires-Dist: scipy
Requires-Dist: statsmodels
Requires-Dist: scikit-learn
Requires-Dist: progressbar2
Requires-Dist: requests
